Metadata-Version: 1.0
Name: fortinetapi
Version: 0.1
Summary: Fortinet API
Home-page: https://gitlab.com/elevenpaths/fortinet-api
Author: Henrique Caires
Author-email: henrique@caires.net.br
License: MIT
Platform: UNKNOWN
